{"cameraMode":{"drawMode":0,"name":"Shaded","section":"Shading Mode"},"sceneLighting":true,"audioPlay":false,"sceneViewState":{"showFog":true,"showMaterialUpdate":false,"showSkybox":true,"showFlares":true,"showImageEffects":true,"showParticleSystems":true},"in2DMode":false,"pivot":{"x":-11.507467269897461,"y":-20.237545013427736,"z":51.89606475830078},"rotation":{"x":-0.17689652740955354,"y":0.10225330293178559,"z":-0.018480729311704637,"w":-0.9787290096282959},"size":64.00841522216797,"orthographic":false}